crepr/__init__.py
crepr/about.py
crepr/crepr.py
crepr/py.typed
crepr-0.6.0.dist-info/licenses/LICENSE
crepr-0.6.0.dist-info/METADATA
crepr-0.6.0.dist-info/WHEEL
crepr-0.6.0.dist-info/entry_points.txt
crepr-0.6.0.dist-info/top_level.txt
crepr-0.6.0.dist-info/RECORD
