Metadata-Version: 2.4
Name: crepr
Version: 0.6.0
Summary: Create a __repr__ for your python classes from the definition found in __init__
Author-email: Christian Ledermann <christian.ledermann@gmail.com>
License: MIT
Project-URL: Homepage, https://github.com/cleder/crepr/
Keywords: __repr__,cli,code generator,introspection
Classifier: Development Status :: 4 - Beta
Classifier: Environment :: Console
Classifier: Intended Audience :: Developers
Classifier: License :: OSI Approved :: MIT License
Classifier: Operating System :: OS Independent
Classifier: Programming Language :: Python
Classifier: Programming Language :: Python :: 3.12
Classifier: Programming Language :: Python :: 3.13
Classifier: Programming Language :: Python :: Implementation :: CPython
Classifier: Programming Language :: Python :: Implementation :: PyPy
Classifier: Topic :: Software Development :: Code Generators
Classifier: Typing :: Typed
Requires-Python: >=3.12
License-File: LICENSE
Requires-Dist: typer-slim>=0.16.1
Provides-Extra: complexity
Requires-Dist: complexipy; extra == "complexity"
Requires-Dist: lizard; extra == "complexity"
Requires-Dist: radon; extra == "complexity"
Provides-Extra: dev
Requires-Dist: crepr[complexity]; extra == "dev"
Requires-Dist: crepr[linting]; extra == "dev"
Requires-Dist: crepr[tests]; extra == "dev"
Requires-Dist: crepr[typing]; extra == "dev"
Requires-Dist: pre-commit; extra == "dev"
Provides-Extra: linting
Requires-Dist: ruff; extra == "linting"
Requires-Dist: yamllint; extra == "linting"
Provides-Extra: tests
Requires-Dist: pytest; extra == "tests"
Requires-Dist: pytest-cov; extra == "tests"
Provides-Extra: typing
Requires-Dist: mypy; extra == "typing"
Dynamic: license-file
